[
  {
    "name": "Ocean Floor (185)",
    "artist": "Midnight Pilot",
    "year": 2024,
    "genres": "synthwave, electro-pop",
    "playlistId": 1
  },
  {
    "name": "A Million Suns (81)",
    "artist": "Stone Age Synth",
    "year": 2025,
    "genres": "progressive house, techno",
    "playlistId": 5
  },
  {
    "name": "Analog Sunset (169)",
    "artist": "Midnight Pilot",
    "year": 2020,
    "genres": "garage rock, punk",
    "playlistId": 2
  },
  {
    "name": "Solar Whisper (54)",
    "artist": "Zenith Core",
    "year": 2020,
    "genres": "industrial, darkwave",
    "playlistId": 2
  },
  {
    "name": "Analog Sunset (78)",
    "artist": "Zenith Core",
    "year": 2025,
    "genres": "grunge revival, alt-rock",
    "playlistId": 5
  },
  {
    "name": "Deep Dive (43)",
    "artist": "Aura X",
    "year": 2024,
    "genres": "trip hop, downtempo",
    "playlistId": 3
  },
  {
    "name": "Neon Dreams (93)",
    "artist": "Luna Dial",
    "year": 2024,
    "genres": "dreampop, ambient",
    "playlistId": 4
  },
  {
    "name": "Galaxy Gossip (105)",
    "artist": "Zenith Core",
    "year": 2025,
    "genres": "synthwave, electro-pop",
    "playlistId": 5
  },
  {
    "name": "Golden Cage (147)",
    "artist": "Indigo Bloom",
    "year": 2025,
    "genres": "indie rock, jangle pop",
    "playlistId": 4
  },
  {
    "name": "A Million Suns (142)",
    "artist": "Midnight Pilot",
    "year": 2020,
    "genres": "synthwave, electro-pop",
    "playlistId": 5
  },
  {
    "name": "River Flow (75)",
    "artist": "The Vinyl Vault",
    "year": 2024,
    "genres": "chillwave, synth-pop",
    "playlistId": 5
  },
  {
    "name": "Stardust Serenade (145)",
    "artist": "Juno 5",
    "year": 2024,
    "genres": "progressive house, techno",
    "playlistId": 2
  },
  {
    "name": "Solar Whisper (191)",
    "artist": "Zenith Core",
    "year": 2024,
    "genres": "garage rock, punk",
    "playlistId": 3
  },
  {
    "name": "Shadow Dance (109)",
    "artist": "Driftwood Collective",
    "year": 2025,
    "genres": "disco revival, funk",
    "playlistId": 2
  },
  {
    "name": "Cosmic Compass (155)",
    "artist": "Stone Age Synth",
    "year": 2020,
    "genres": "pop, dancehall",
    "playlistId": 1
  },
  {
    "name": "Wildfire Heart (159)",
    "artist": "Aura X",
    "year": 2024,
    "genres": "folk-tronica, acoustic",
    "playlistId": 5
  },
  {
    "name": "Solar Whisper (108)",
    "artist": "Indigo Bloom",
    "year": 2025,
    "genres": "progressive house, techno",
    "playlistId": 3
  },
  {
    "name": "Moonlit Bloom (16)",
    "artist": "Zenith Core",
    "year": 2020,
    "genres": "grunge revival, alt-rock",
    "playlistId": 4
  },
  {
    "name": "A Million Suns (143)",
    "artist": "Lunar Dial",
    "year": 2025,
    "genres": "disco revival, funk",
    "playlistId": 5
  },
  {
    "name": "The Last Train (44)",
    "artist": "The Quantum Leap",
    "year": 2024,
    "genres": "trap, lo-fi",
    "playlistId": 1
  }
]